pnglatex/__init__.py
pnglatex/pnglatex.py
pnglatex-1.1.dist-info/DESCRIPTION.rst
pnglatex-1.1.dist-info/LICENSE.txt
pnglatex-1.1.dist-info/METADATA
pnglatex-1.1.dist-info/RECORD
pnglatex-1.1.dist-info/WHEEL
pnglatex-1.1.dist-info/entry_points.txt
pnglatex-1.1.dist-info/metadata.json
pnglatex-1.1.dist-info/top_level.txt
