Metadata-Version: 2.0
Name: pnglatex
Version: 1.1
Summary: A small program that converts latex snippets to png
Home-page: https://github.com/MaT1g3R/pnglatex
Author: Peijun Ma
Author-email: mat1g3r@gmail.com
License: GPLv3+
Platform: UNKNOWN
Classifier: License :: OSI Approved :: GNU General Public License v3 or later (GPLv3+)
Classifier: Natural Language :: English
Classifier: Operating System :: POSIX
Classifier: Programming Language :: Python :: 3
Classifier: Topic :: Text Processing :: Markup :: LaTeX
Classifier: Topic :: Utilities
Classifier: Topic :: Multimedia :: Graphics :: Graphics Conversion
Classifier: Environment :: Console
Classifier: Intended Audience :: Developers
Classifier: Intended Audience :: End Users/Desktop
Classifier: Intended Audience :: Education
Classifier: Development Status :: 5 - Production/Stable
